pgpdump3-1.5.2.dist-info/RECORD
pgpdump3-1.5.2.dist-info/top_level.txt
pgpdump3-1.5.2.dist-info/METADATA
pgpdump3-1.5.2.dist-info/WHEEL
pgpdump3-1.5.2.dist-info/DESCRIPTION.rst
pgpdump3-1.5.2.dist-info/metadata.json
pgpdump/__main__.py
pgpdump/utils.py
pgpdump/packet.py
pgpdump/__init__.py
pgpdump/data.py
