Metadata-Version: 2.0
Name: pgpdump3
Version: 1.5.2
Summary: PGP packet parser library
Home-page: https://github.com/SkierPGP/python-pgpdump
Author: Dan McGee, Isaac Dickinson
Author-email: UNKNOWN
License: BSD
Keywords: pgp gpg rfc2440 rfc4880 crypto cryptography
Platform: UNKNOWN
Classifier: Development Status :: 4 - Beta
Classifier: Intended Audience :: Developers
Classifier: License :: OSI Approved :: BSD License
Classifier: Programming Language :: Python
Classifier: Programming Language :: Python :: 3
Classifier: Topic :: Security :: Cryptography
Classifier: Topic :: Software Development :: Libraries :: Python Modules
